<?xml version="1.0" encoding="UTF-8"?>
<objects serializationModel="Studio.02.01.00">
	<object class="AudioFile" id="{62f54a76-b810-4ac0-a68e-4a5bce61a21e}">
		<property name="assetPath">
			<value>Shrek1VHS_Part1-cm-cm-cm_08-02.wav</value>
		</property>
		<property name="frequencyInKHz">
			<value>48</value>
		</property>
		<property name="channelCount">
			<value>2</value>
		</property>
		<property name="length">
			<value>1.0962708333333333</value>
		</property>
		<relationship name="masterAssetFolder">
			<destination>{94be6338-ee5a-4c40-bfea-8c07387945e6}</destination>
		</relationship>
	</object>
</objects>
